envconfiguration/__init__.py
envconfiguration/envconfiguration.py
envconfiguration-0.1.0.dist-info/METADATA
envconfiguration-0.1.0.dist-info/WHEEL
envconfiguration-0.1.0.dist-info/top_level.txt
envconfiguration-0.1.0.dist-info/RECORD
