Metadata-Version: 2.1
Name: envconfiguration
Version: 0.1.0
Summary: Enviroment configuration
Home-page: https://github.com/gpcortes/envconfiguration.git
Author: Gustavo Côrtes
Author-email: gpcortes@gmail.com
License: BSD 2-clause
Classifier: Development Status :: 1 - Planning
Classifier: Intended Audience :: Science/Research
Classifier: License :: OSI Approved :: BSD License
Classifier: Operating System :: POSIX :: Linux
Classifier: Programming Language :: Python :: 3.7
Requires-Dist: python-dotenv (>=0.21.0)
